randomly/__init__.py
randomly/clustering.py
randomly/palettes.py
randomly/randomly.py
randomly/visualization.py
randomly-0.1.5.dist-info/AUTHORS.rst
randomly-0.1.5.dist-info/LICENSE
randomly-0.1.5.dist-info/METADATA
randomly-0.1.5.dist-info/WHEEL
randomly-0.1.5.dist-info/top_level.txt
randomly-0.1.5.dist-info/RECORD
