Metadata-Version: 2.1
Name: randomly
Version: 0.1.5
Summary: A Library for Denoising Single-Cell Data with Random Matrix Theory
Home-page: https://github.com/RabadanLab/randomly
Author: Luis Aparicio
Author-email: la2666@cumc.columbia.edu
License: MIT license
Keywords: randomly
Platform: UNKNOWN
Classifier: Development Status :: 4 - Beta
Classifier: Intended Audience :: Developers
Classifier: License :: OSI Approved :: MIT License
Classifier: Natural Language :: English
Classifier: Programming Language :: Python :: 3
Classifier: Programming Language :: Python :: 3.4
Classifier: Programming Language :: Python :: 3.5
Classifier: Programming Language :: Python :: 3.6
Classifier: Programming Language :: Python :: 3.7
Requires-Dist: pandas (>=0.23.4)
Requires-Dist: scipy (>=1.1.0)
Requires-Dist: matplotlib (>=2.2.3)
Requires-Dist: seaborn (>=0.9.0)
Requires-Dist: scikit-learn (>=0.19.2)
Requires-Dist: MulticoreTSNE (>=0.0.1.1)
